{
  "project_info": {
    "project_number": "533482325084",
    "project_id": "concept-f9dba",
    "storage_bucket": "concept-f9dba.appspot.com"
  },
  "client": [
    {
      "client_info": {
        "mobilesdk_app_id": "1:533482325084:android:f885b9aafc7aea97f49299",
        "android_client_info": {
          "package_name": "com.example.concept"
        }
      },
      "oauth_client": [
        {
          "client_id": "533482325084-eva0crmvc6jn1csjk1mt0v6thgtvooba.apps.googleusercontent.com",
          "client_type": 1,
          "android_info": {
            "package_name": "com.example.concept",
            "certificate_hash": "5954a2ff23651a7f4968514fbbfb58d6eda4caea"
          }
        },
        {
          "client_id": "533482325084-emf7k0qrrnuj37qfi0ukhd1vfc1o2nls.apps.googleusercontent.com",
          "client_type": 3
        }
      ],
      "api_key": [
        {
          "current_key": "AIzaSyDVtdQXTRHpkW-DyAoMUn8BmRMKFcpfVXM"
        }
      ],
      "services": {
        "appinvite_service": {
          "other_platform_oauth_client": [
            {
              "client_id": "533482325084-emf7k0qrrnuj37qfi0ukhd1vfc1o2nls.apps.googleusercontent.com",
              "client_type": 3
            }
          ]
        }
      }
    }
  ],
  "configuration_version": "1"
}